scriptmate/__init__.py
scriptmate/__main__.py
scriptmate/cli.py
scriptmate/config.py
scriptmate/executor.py
scriptmate/llm_client.py
scriptmate/utils.py
scriptmate-0.1.0.dist-info/METADATA
scriptmate-0.1.0.dist-info/WHEEL
scriptmate-0.1.0.dist-info/entry_points.txt
scriptmate-0.1.0.dist-info/licenses/LICENSE
scriptmate-0.1.0.dist-info/RECORD
