Metadata-Version: 2.4
Name: scriptmate
Version: 0.1.0
Summary: ScriptMate - Intelligent Script Companion
Project-URL: Homepage, https://github.com/scriptmate/scriptmate
Project-URL: Repository, https://github.com/scriptmate/scriptmate.git
Project-URL: Documentation, https://scriptmate.readthedocs.io
Project-URL: Bug Tracker, https://github.com/scriptmate/scriptmate/issues
Author-email: ScriptMate Team <jubaoliang@gmail.com>
License-Expression: MIT
License-File: LICENSE
Keywords: ai,cli,command,natural-language,shell
Classifier: Development Status :: 4 - Beta
Classifier: Intended Audience :: Developers
Classifier: License :: OSI Approved :: MIT License
Classifier: Operating System :: OS Independent
Classifier: Programming Language :: Python :: 3
Classifier: Programming Language :: Python :: 3.8
Classifier: Programming Language :: Python :: 3.9
Classifier: Programming Language :: Python :: 3.10
Classifier: Programming Language :: Python :: 3.11
Classifier: Programming Language :: Python :: 3.12
Classifier: Topic :: Software Development :: Libraries :: Python Modules
Classifier: Topic :: System :: Shells
Classifier: Topic :: Utilities
Requires-Python: >=3.8
Requires-Dist: click>=8.0.0
Requires-Dist: requests>=2.25.0
Requires-Dist: rich>=10.0.0
Provides-Extra: dev
Requires-Dist: black>=21.0.0; extra == 'dev'
Requires-Dist: flake8>=3.8.0; extra == 'dev'
Requires-Dist: mypy>=0.800; extra == 'dev'
Requires-Dist: pytest-cov>=2.10.0; extra == 'dev'
Requires-Dist: pytest>=6.0.0; extra == 'dev'
